[
  {
    "content": "Login Page: Remove 'AidHub Pro' and 'University Financial Aid Platform' text",
    "status": "completed"
  },
  {
    "content": "Middle panel empty state: Remove email icon",
    "status": "completed"
  },
  {
    "content": "Replace AidHub Pro logo with Peach logo (SVG) in top navigation",
    "status": "completed"
  },
  {
    "content": "Change ticket numbers from 8-char UUID to random 4-digit format (#1234)",
    "status": "completed"
  },
  {
    "content": "Test all branding changes",
    "status": "completed"
  }
]